avin_data/__init__.py
avin_data/cli.py
avin_data/manager/__init__.py
avin_data/manager/category.py
avin_data/manager/data_file_bar.py
avin_data/manager/data_file_tic.py
avin_data/manager/exchange.py
avin_data/manager/iid.py
avin_data/manager/iid_cache.py
avin_data/manager/manager.py
avin_data/manager/market_data.py
avin_data/manager/source.py
avin_data/manager/source_moex.py
avin_data/utils/__init__.py
avin_data/utils/cmd.py
avin_data/utils/conf.py
avin_data/utils/logger.py
avin_data/utils/misc.py
avin_data-1.1.0.dist-info/entry_points.txt
avin_data-1.1.0.dist-info/licenses/LICENSE
avin_data-1.1.0.dist-info/WHEEL
avin_data-1.1.0.dist-info/METADATA
avin_data-1.1.0.dist-info/RECORD
