Metadata-Version: 2.4
Name: avin_data
Version: 1.1.0
Summary: CLI utility for download market data
Author-email: Alex Avin <mr.alexavin@gmail.com>
Requires-Python: >=3.12
License-Expression: MIT
License-File: LICENSE
Requires-Dist: click>=8.1
Requires-Dist: flit
Requires-Dist: httpx
Requires-Dist: moexalgo
Requires-Dist: numpy
Requires-Dist: pandas
Requires-Dist: polars
Requires-Dist: polars-lts-cpu
Requires-Dist: pyarrow
Requires-Dist: pytest
Requires-Dist: pytest-asyncio
Requires-Dist: tinkoff-investments
